{
  "version": "7",
  "dialect": "sqlite",
  "entries": [
    {
      "idx": 0,
      "version": "6",
      "when": 1772943423964,
      "tag": "0000_slimy_next_avengers",
      "breakpoints": true
    },
    {
      "idx": 1,
      "version": "6",
      "when": 1772944656961,
      "tag": "0001_rare_titanium_man",
      "breakpoints": true
    },
    {
      "idx": 2,
      "version": "6",
      "when": 1772945216269,
      "tag": "0002_cuddly_senator_kelly",
      "breakpoints": true
    },
    {
      "idx": 3,
      "version": "6",
      "when": 1772946209733,
      "tag": "0003_nasty_plazm",
      "breakpoints": true
    },
    {
      "idx": 4,
      "version": "6",
      "when": 1772947819605,
      "tag": "0004_stiff_machine_man",
      "breakpoints": true
    },
    {
      "idx": 5,
      "version": "6",
      "when": 1772948947293,
      "tag": "0005_mushy_crusher_hogan",
      "breakpoints": true
    },
    {
      "idx": 6,
      "version": "6",
      "when": 1772949546513,
      "tag": "0006_remarkable_punisher",
      "breakpoints": true
    },
    {
      "idx": 7,
      "version": "6",
      "when": 1772953075550,
      "tag": "0007_wonderful_blizzard",
      "breakpoints": true
    }
  ]
}